[
 {
  "docstatus": 0,
  "doctype": "Workflow",
  "document_type": "Leave Request Pro",
  "enable_action_confirmation": 0,
  "is_active": 1,
  "modified": "2026-04-19 00:46:18.780598",
  "name": "Leave Approval Workflow",
  "override_status": 0,
  "send_email_alert": 1,
  "states": [
   {
    "allow_edit": "All",
    "avoid_status_override": 0,
    "doc_status": "0",
    "evaluate_as_expression": 0,
    "is_optional_state": 0,
    "message": null,
    "next_action_email_template": null,
    "send_email": 1,
    "state": "Draft",
    "update_field": "status",
    "update_value": "Draft",
    "workflow_builder_id": null
   },
   {
    "allow_edit": "Leave Manager",
    "avoid_status_override": 0,
    "doc_status": "0",
    "evaluate_as_expression": 0,
    "is_optional_state": 0,
    "message": null,
    "next_action_email_template": null,
    "send_email": 1,
    "state": "Pending Manager",
    "update_field": "status",
    "update_value": "Pending Manager",
    "workflow_builder_id": null
   },
   {
    "allow_edit": "Leave HR",
    "avoid_status_override": 0,
    "doc_status": "0",
    "evaluate_as_expression": 0,
    "is_optional_state": 0,
    "message": null,
    "next_action_email_template": null,
    "send_email": 1,
    "state": "Pending HR",
    "update_field": "status",
    "update_value": "Pending HR",
    "workflow_builder_id": null
   },
   {
    "allow_edit": "All",
    "avoid_status_override": 0,
    "doc_status": "0",
    "evaluate_as_expression": 0,
    "is_optional_state": 0,
    "message": null,
    "next_action_email_template": null,
    "send_email": 1,
    "state": "Approved",
    "update_field": "status",
    "update_value": "Approved",
    "workflow_builder_id": null
   },
   {
    "allow_edit": "All",
    "avoid_status_override": 0,
    "doc_status": "0",
    "evaluate_as_expression": 0,
    "is_optional_state": 0,
    "message": null,
    "next_action_email_template": null,
    "send_email": 1,
    "state": "Rejected",
    "update_field": "status",
    "update_value": "Rejected",
    "workflow_builder_id": null
   },
   {
    "allow_edit": "All",
    "avoid_status_override": 0,
    "doc_status": "0",
    "evaluate_as_expression": 0,
    "is_optional_state": 0,
    "message": null,
    "next_action_email_template": null,
    "send_email": 1,
    "state": "Escalated",
    "update_field": "status",
    "update_value": "Escalated",
    "workflow_builder_id": null
   }
  ],
  "transitions": [
   {
    "action": "Submit for Approval",
    "allow_self_approval": 1,
    "allowed": "All",
    "condition": null,
    "next_state": "Pending Manager",
    "send_email_to_creator": 0,
    "state": "Draft",
    "transition_tasks": null,
    "workflow_builder_id": null
   },
   {
    "action": "Approve",
    "allow_self_approval": 1,
    "allowed": "Leave Manager",
    "condition": null,
    "next_state": "Pending HR",
    "send_email_to_creator": 0,
    "state": "Pending Manager",
    "transition_tasks": null,
    "workflow_builder_id": null
   },
   {
    "action": "Reject",
    "allow_self_approval": 1,
    "allowed": "Leave Manager",
    "condition": null,
    "next_state": "Rejected",
    "send_email_to_creator": 0,
    "state": "Pending Manager",
    "transition_tasks": null,
    "workflow_builder_id": null
   },
   {
    "action": "Approve",
    "allow_self_approval": 1,
    "allowed": "Leave HR",
    "condition": null,
    "next_state": "Approved",
    "send_email_to_creator": 0,
    "state": "Pending HR",
    "transition_tasks": null,
    "workflow_builder_id": null
   },
   {
    "action": "Reject",
    "allow_self_approval": 1,
    "allowed": "Leave HR",
    "condition": null,
    "next_state": "Rejected",
    "send_email_to_creator": 0,
    "state": "Pending HR",
    "transition_tasks": null,
    "workflow_builder_id": null
   },
   {
    "action": "Escalate",
    "allow_self_approval": 1,
    "allowed": "Leave HR",
    "condition": null,
    "next_state": "Escalated",
    "send_email_to_creator": 0,
    "state": "Pending HR",
    "transition_tasks": null,
    "workflow_builder_id": null
   }
  ],
  "workflow_data": null,
  "workflow_name": "Leave Approval Workflow",
  "workflow_state_field": "workflow_state"
 },
 {
  "docstatus": 0,
  "doctype": "Workflow",
  "document_type": "Client Project Onboarding",
  "enable_action_confirmation": 0,
  "is_active": 1,
  "modified": "2026-04-19 19:24:08.002682",
  "name": "Client Onboarding Workflow",
  "override_status": 0,
  "send_email_alert": 1,
  "states": [
   {
    "allow_edit": "Project Manager",
    "avoid_status_override": 0,
    "doc_status": "0",
    "evaluate_as_expression": 0,
    "is_optional_state": 0,
    "message": null,
    "next_action_email_template": null,
    "send_email": 1,
    "state": "Draft",
    "update_field": "status",
    "update_value": "Draft",
    "workflow_builder_id": null
   },
   {
    "allow_edit": "Tech Lead",
    "avoid_status_override": 0,
    "doc_status": "0",
    "evaluate_as_expression": 0,
    "is_optional_state": 0,
    "message": null,
    "next_action_email_template": null,
    "send_email": 1,
    "state": "Kickoff Scheduled",
    "update_field": "status",
    "update_value": "Kickoff Scheduled",
    "workflow_builder_id": null
   },
   {
    "allow_edit": "Project Manager",
    "avoid_status_override": 0,
    "doc_status": "0",
    "evaluate_as_expression": 0,
    "is_optional_state": 0,
    "message": null,
    "next_action_email_template": null,
    "send_email": 1,
    "state": "In Progress",
    "update_field": "status",
    "update_value": "In Progress",
    "workflow_builder_id": null
   },
   {
    "allow_edit": "Project Manager",
    "avoid_status_override": 0,
    "doc_status": "0",
    "evaluate_as_expression": 0,
    "is_optional_state": 0,
    "message": null,
    "next_action_email_template": null,
    "send_email": 1,
    "state": "On Hold",
    "update_field": "status",
    "update_value": "On Hold",
    "workflow_builder_id": null
   },
   {
    "allow_edit": "All",
    "avoid_status_override": 0,
    "doc_status": "0",
    "evaluate_as_expression": 0,
    "is_optional_state": 0,
    "message": null,
    "next_action_email_template": null,
    "send_email": 1,
    "state": "Completed",
    "update_field": "status",
    "update_value": "Completed",
    "workflow_builder_id": null
   }
  ],
  "transitions": [
   {
    "action": "Schedule Kickoff",
    "allow_self_approval": 1,
    "allowed": "Project Manager",
    "condition": null,
    "next_state": "Kickoff Scheduled",
    "send_email_to_creator": 0,
    "state": "Draft",
    "transition_tasks": null,
    "workflow_builder_id": null
   },
   {
    "action": "Confirm Kickoff",
    "allow_self_approval": 1,
    "allowed": "Tech Lead",
    "condition": null,
    "next_state": "In Progress",
    "send_email_to_creator": 0,
    "state": "Kickoff Scheduled",
    "transition_tasks": null,
    "workflow_builder_id": null
   },
   {
    "action": "Mark Complete",
    "allow_self_approval": 1,
    "allowed": "Project Manager",
    "condition": null,
    "next_state": "Completed",
    "send_email_to_creator": 0,
    "state": "In Progress",
    "transition_tasks": null,
    "workflow_builder_id": null
   },
   {
    "action": "Put on Hold",
    "allow_self_approval": 1,
    "allowed": "Project Manager",
    "condition": null,
    "next_state": "On Hold",
    "send_email_to_creator": 0,
    "state": "In Progress",
    "transition_tasks": null,
    "workflow_builder_id": null
   },
   {
    "action": "Resume",
    "allow_self_approval": 1,
    "allowed": "Project Manager",
    "condition": null,
    "next_state": "In Progress",
    "send_email_to_creator": 0,
    "state": "On Hold",
    "transition_tasks": null,
    "workflow_builder_id": null
   }
  ],
  "workflow_data": null,
  "workflow_name": "Client Onboarding Workflow",
  "workflow_state_field": "workflow_state"
 },
 {
  "docstatus": 0,
  "doctype": "Workflow",
  "document_type": "Performance Review",
  "enable_action_confirmation": 0,
  "is_active": 1,
  "modified": "2026-04-19 22:57:30.077668",
  "name": "Performance Review Workflow",
  "override_status": 0,
  "send_email_alert": 1,
  "states": [
   {
    "allow_edit": "Appraisal Manager",
    "avoid_status_override": 0,
    "doc_status": "0",
    "evaluate_as_expression": 0,
    "is_optional_state": 0,
    "message": null,
    "next_action_email_template": null,
    "send_email": 1,
    "state": "Draft",
    "update_field": "final_status",
    "update_value": "Draft",
    "workflow_builder_id": null
   },
   {
    "allow_edit": "HR Manager",
    "avoid_status_override": 0,
    "doc_status": "0",
    "evaluate_as_expression": 0,
    "is_optional_state": 0,
    "message": null,
    "next_action_email_template": null,
    "send_email": 1,
    "state": "Under Review",
    "update_field": "final_status",
    "update_value": "Under Review",
    "workflow_builder_id": null
   },
   {
    "allow_edit": "Employee",
    "avoid_status_override": 0,
    "doc_status": "0",
    "evaluate_as_expression": 0,
    "is_optional_state": 0,
    "message": null,
    "next_action_email_template": null,
    "send_email": 1,
    "state": "Acknowledged",
    "update_field": "final_status",
    "update_value": "Acknowledged",
    "workflow_builder_id": null
   },
   {
    "allow_edit": "All",
    "avoid_status_override": 0,
    "doc_status": "0",
    "evaluate_as_expression": 0,
    "is_optional_state": 0,
    "message": null,
    "next_action_email_template": null,
    "send_email": 1,
    "state": "Closed",
    "update_field": "final_status",
    "update_value": "Closed",
    "workflow_builder_id": null
   }
  ],
  "transitions": [
   {
    "action": "Submit for Review",
    "allow_self_approval": 1,
    "allowed": "Appraisal Manager",
    "condition": null,
    "next_state": "Under Review",
    "send_email_to_creator": 0,
    "state": "Draft",
    "transition_tasks": null,
    "workflow_builder_id": null
   },
   {
    "action": "Share with Employee",
    "allow_self_approval": 1,
    "allowed": "HR Manager",
    "condition": null,
    "next_state": "Acknowledged",
    "send_email_to_creator": 0,
    "state": "Under Review",
    "transition_tasks": null,
    "workflow_builder_id": null
   },
   {
    "action": "Close Review",
    "allow_self_approval": 1,
    "allowed": "HR Manager",
    "condition": null,
    "next_state": "Closed",
    "send_email_to_creator": 0,
    "state": "Acknowledged",
    "transition_tasks": null,
    "workflow_builder_id": null
   }
  ],
  "workflow_data": null,
  "workflow_name": "Performance Review Workflow",
  "workflow_state_field": "workflow_state"
 },
 {
  "docstatus": 0,
  "doctype": "Workflow",
  "document_type": "Monthly Payroll Run",
  "enable_action_confirmation": 0,
  "is_active": 1,
  "modified": "2026-05-02 12:55:23.127386",
  "name": "Payroll Approval Workflow",
  "override_status": 0,
  "send_email_alert": 1,
  "states": [
   {
    "allow_edit": "HR Manager",
    "avoid_status_override": 0,
    "doc_status": "0",
    "evaluate_as_expression": 0,
    "is_optional_state": 0,
    "message": null,
    "next_action_email_template": null,
    "send_email": 1,
    "state": "Draft",
    "update_field": "status",
    "update_value": "Draft",
    "workflow_builder_id": null
   },
   {
    "allow_edit": "HR Manager",
    "avoid_status_override": 0,
    "doc_status": "0",
    "evaluate_as_expression": 0,
    "is_optional_state": 0,
    "message": null,
    "next_action_email_template": null,
    "send_email": 1,
    "state": "Pending HR Approval",
    "update_field": "status",
    "update_value": "Pending HR Approval",
    "workflow_builder_id": null
   },
   {
    "allow_edit": "Finance Head",
    "avoid_status_override": 0,
    "doc_status": "0",
    "evaluate_as_expression": 0,
    "is_optional_state": 0,
    "message": null,
    "next_action_email_template": null,
    "send_email": 1,
    "state": "Pending Finance Approval",
    "update_field": "status",
    "update_value": "Pending HR Approval",
    "workflow_builder_id": null
   },
   {
    "allow_edit": "CEO",
    "avoid_status_override": 0,
    "doc_status": "0",
    "evaluate_as_expression": 0,
    "is_optional_state": 0,
    "message": null,
    "next_action_email_template": null,
    "send_email": 1,
    "state": "Pending CEO Approval",
    "update_field": "status",
    "update_value": "Pending CEO Approval",
    "workflow_builder_id": null
   },
   {
    "allow_edit": "System Manager",
    "avoid_status_override": 0,
    "doc_status": "1",
    "evaluate_as_expression": 0,
    "is_optional_state": 0,
    "message": null,
    "next_action_email_template": null,
    "send_email": 1,
    "state": "Approved",
    "update_field": "status",
    "update_value": "Approved",
    "workflow_builder_id": null
   }
  ],
  "transitions": [
   {
    "action": "Submit for HR Approval",
    "allow_self_approval": 1,
    "allowed": "HR Manager",
    "condition": null,
    "next_state": "Pending HR Approval",
    "send_email_to_creator": 0,
    "state": "Draft",
    "transition_tasks": null,
    "workflow_builder_id": null
   },
   {
    "action": "Approve",
    "allow_self_approval": 1,
    "allowed": "HR Manager",
    "condition": null,
    "next_state": "Pending Finance Approval",
    "send_email_to_creator": 0,
    "state": "Pending HR Approval",
    "transition_tasks": null,
    "workflow_builder_id": null
   },
   {
    "action": "Approve",
    "allow_self_approval": 1,
    "allowed": "Finance Head",
    "condition": null,
    "next_state": "Pending CEO Approval",
    "send_email_to_creator": 0,
    "state": "Pending Finance Approval",
    "transition_tasks": null,
    "workflow_builder_id": null
   },
   {
    "action": "Approve",
    "allow_self_approval": 1,
    "allowed": "CEO",
    "condition": null,
    "next_state": "Approved",
    "send_email_to_creator": 0,
    "state": "Pending CEO Approval",
    "transition_tasks": null,
    "workflow_builder_id": null
   }
  ],
  "workflow_data": null,
  "workflow_name": "Payroll Approval Workflow",
  "workflow_state_field": "workflow_state"
 }
]